[{
  "_id": {
    "$oid": "61c9c36ea5e4bb53ca476b03"
  },
  "name": "צדק",
  "stream_name": "king.wav",
  "part": "0 - 2"
},{
  "_id": {
    "$oid": "61c9c36ea5e4bb53ca476b04"
  },
  "name": "בחיים",
  "stream_name": "king.wav",
  "part": "0 - 2"
},{
  "_id": {
    "$oid": "61c9c36ea5e4bb53ca476b05"
  },
  "name": "הקטן",
  "stream_name": "king.wav",
  "part": "0 - 2"
},{
  "_id": {
    "$oid": "61c9c36ea5e4bb53ca476b06"
  },
  "name": "בזמן",
  "stream_name": "king.wav",
  "part": "0 - 2"
},{
  "_id": {
    "$oid": "61c9c36ea5e4bb53ca476b07"
  },
  "name": "שחלק",
  "stream_name": "king.wav",
  "part": "0 - 2"
},{
  "_id": {
    "$oid": "61c9c36ea5e4bb53ca476b08"
  },
  "name": "נולדו",
  "stream_name": "king.wav",
  "part": "0 - 2"
},{
  "_id": {
    "$oid": "61c9c36ea5e4bb53ca476b09"
  },
  "name": "לחגוג",
  "stream_name": "king.wav",
  "part": "0 - 2"
},{
  "_id": {
    "$oid": "61c9c36ea5e4bb53ca476b0a"
  },
  "name": "אחרים",
  "stream_name": "king.wav",
  "part": "0 - 2"
},{
  "_id": {
    "$oid": "61c9c36ea5e4bb53ca476b0b"
  },
  "name": "מעבירים",
  "stream_name": "king.wav",
  "part": "0 - 2"
},{
  "_id": {
    "$oid": "61c9c36ea5e4bb53ca476b0c"
  },
  "name": "את",
  "stream_name": "king.wav",
  "part": "0 - 2"
},{
  "_id": {
    "$oid": "61c9c383a5e4bb53ca476b0e"
  },
  "name": "צדק",
  "stream_name": "king.wav",
  "part": "1 - 3"
},{
  "_id": {
    "$oid": "61c9c383a5e4bb53ca476b0f"
  },
  "name": "בחיים",
  "stream_name": "king.wav",
  "part": "1 - 3"
},{
  "_id": {
    "$oid": "61c9c383a5e4bb53ca476b10"
  },
  "name": "הקטן",
  "stream_name": "king.wav",
  "part": "1 - 3"
},{
  "_id": {
    "$oid": "61c9c383a5e4bb53ca476b11"
  },
  "name": "בזמן",
  "stream_name": "king.wav",
  "part": "1 - 3"
},{
  "_id": {
    "$oid": "61c9c383a5e4bb53ca476b12"
  },
  "name": "שחלק",
  "stream_name": "king.wav",
  "part": "1 - 3"
},{
  "_id": {
    "$oid": "61c9c383a5e4bb53ca476b13"
  },
  "name": "נולדו",
  "stream_name": "king.wav",
  "part": "1 - 3"
},{
  "_id": {
    "$oid": "61c9c383a5e4bb53ca476b14"
  },
  "name": "לחגוג",
  "stream_name": "king.wav",
  "part": "1 - 3"
},{
  "_id": {
    "$oid": "61c9c383a5e4bb53ca476b15"
  },
  "name": "אחרים",
  "stream_name": "king.wav",
  "part": "1 - 3"
},{
  "_id": {
    "$oid": "61c9c383a5e4bb53ca476b16"
  },
  "name": "מעבירים",
  "stream_name": "king.wav",
  "part": "1 - 3"
},{
  "_id": {
    "$oid": "61c9c383a5e4bb53ca476b17"
  },
  "name": "את",
  "stream_name": "king.wav",
  "part": "1 - 3"
}]